odoo/addons/runbot_subject_skip/README.rst
odoo/addons/runbot_subject_skip/__init__.py
odoo/addons/runbot_subject_skip/__manifest__.py
odoo/addons/runbot_subject_skip/models/__init__.py
odoo/addons/runbot_subject_skip/models/runbot_build.py
odoo/addons/runbot_subject_skip/tests/__init__.py
odoo/addons/runbot_subject_skip/tests/test_runbot_skip_build.py
odoo11_addon_runbot_subject_skip-11.0.1.0.0.dist-info/DESCRIPTION.rst
odoo11_addon_runbot_subject_skip-11.0.1.0.0.dist-info/METADATA
odoo11_addon_runbot_subject_skip-11.0.1.0.0.dist-info/RECORD
odoo11_addon_runbot_subject_skip-11.0.1.0.0.dist-info/WHEEL
odoo11_addon_runbot_subject_skip-11.0.1.0.0.dist-info/metadata.json
odoo11_addon_runbot_subject_skip-11.0.1.0.0.dist-info/top_level.txt
